README.rst
setup.py
pyrtg/__init__.py
pyrtg/core.py
pyrtg.egg-info/PKG-INFO
pyrtg.egg-info/SOURCES.txt
pyrtg.egg-info/dependency_links.txt
pyrtg.egg-info/top_level.txt