Metadata-Version: 1.0
Name: pyrtg
Version: 0.2
Summary: Classes for easily generating PRTG XML output.
Home-page: https://github.com/jonpurdy/pyrtg
Author: Jon Purdy
Author-email: jon+pyrtg@jonpurdy.com
License: GNU General Public License v3 (GPLv3)
Platform: UNKNOWN
